bumpuv/__init__.py
bumpuv/__main__.py
bumpuv/_core.py
bumpuv-0.0.5.dist-info/WHEEL
bumpuv-0.0.5.dist-info/entry_points.txt
bumpuv-0.0.5.dist-info/METADATA
bumpuv-0.0.5.dist-info/RECORD
