Metadata-Version: 2.3
Name: bumpuv
Version: 0.0.5
Summary: Version bumping tool for Python projects using pyproject.toml, similar to npm version
Keywords: version,bump,pyproject,git,release,semver
Author: heiwa4126
Author-email: heiwa4126 <heiwa4126@gmail.com>
License: MIT License
Classifier: License :: OSI Approved :: MIT License
Classifier: Operating System :: OS Independent
Classifier: Programming Language :: Python :: 3
Requires-Dist: gitpython>=3.1.0
Requires-Dist: packaging>=21.0
Requires-Dist: tomli>=2.0.0 ; python_full_version < '3.11'
Requires-Dist: tomli-w>=1.0.0
Requires-Dist: colorama>=0.4.0
Requires-Python: >=3.9
Project-URL: Documentation, https://github.com/heiwa4126/bumpuv#readme
Project-URL: Issues, https://github.com/heiwa4126/bumpuv/issues
Project-URL: Source, https://github.com/heiwa4126/bumpuv
